{"format":2,"version":"7.3.2","globals":"c3f39e8a776acbda54efdd8da54480b5","files":{"d_14b3099d61bfdbea___init___py":{"hash":"d1af522fa31d65ed188138fe52624203","index":{"nums":[0,1,6,0,0,0,0,0],"html_filename":"d_14b3099d61bfdbea___init___py.html","relative_filename":"include/__init__.py"}},"d_14b3099d61bfdbea__loss_functions_py":{"hash":"f42f13df2aff07272be42f7e1a3f8198","index":{"nums":[0,1,2,0,0,0,0,0],"html_filename":"d_14b3099d61bfdbea__loss_functions_py.html","relative_filename":"include/_loss_functions.py"}},"d_14b3099d61bfdbea_graph_py":{"hash":"2b099046774fce2a4a358ac4fe99f35a","index":{"nums":[0,1,85,0,79,0,0,0],"html_filename":"d_14b3099d61bfdbea_graph_py.html","relative_filename":"include/graph.py"}},"d_14b3099d61bfdbea_langevin_py":{"hash":"32a413dde112964d288319e672754d09","index":{"nums":[0,1,122,0,105,0,0,0],"html_filename":"d_14b3099d61bfdbea_langevin_py.html","relative_filename":"include/langevin.py"}},"d_14b3099d61bfdbea_neural_net_py":{"hash":"aa842c0f7f85910d048d2efe67b160d9","index":{"nums":[0,1,81,0,67,0,0,0],"html_filename":"d_14b3099d61bfdbea_neural_net_py.html","relative_filename":"include/neural_net.py"}},"d_14b3099d61bfdbea_utils_py":{"hash":"c0e53c1c5f07c19a99e1b05b139985b7","index":{"nums":[0,1,16,0,1,0,0,0],"html_filename":"d_14b3099d61bfdbea_utils_py.html","relative_filename":"include/utils.py"}},"d_14b3099d61bfdbea_vector_py":{"hash":"a0f4c1a7e134161aba94a6c7152c0b39","index":{"nums":[0,1,43,0,25,0,0,0],"html_filename":"d_14b3099d61bfdbea_vector_py.html","relative_filename":"include/vector.py"}},"d_a44f0ac069e85531___init___py":{"hash":"e6baa73cda2916dad605215f937a92e1","index":{"nums":[0,1,0,0,0,0,0,0],"html_filename":"d_a44f0ac069e85531___init___py.html","relative_filename":"tests/__init__.py"}},"d_362576575d76e233_test_utils_py":{"hash":"54167dfc7d582663fc8d10dc4109576f","index":{"nums":[0,1,42,0,2,0,0,0],"html_filename":"d_362576575d76e233_test_utils_py.html","relative_filename":"tests/core/test_utils.py"}}}}